[
  {
    "titulo": "Defunciones por Homicidio 2024 - Comunicado de prensa",
    "autor": "INEGI",
    "institucion": "INEGI",
    "anio": 2025,
    "url": "https://www.inegi.org.mx/contenidos/saladeprensa/boletines/2025/edr/DH2024_CP_Ene-dic.pdf",
    "categoria": "homicidios",
    "numero_paginas": 4,
    "fecha_descarga": "2026-06-03T01:58:54.118555",
    "archivo": "homicidios/homicidios_inegi_2025.pdf"
  },
  {
    "titulo": "Atlas de Homicidios: México 2024",
    "autor": "Mónica Daniela Osorio Reyes",
    "institucion": "MUCD",
    "anio": 2025,
    "url": "https://www.mucd.org.mx/wp-content/uploads/2025/12/Atlas2024.pdf",
    "categoria": "homicidios",
    "numero_paginas": 130,
    "fecha_descarga": "2026-06-03T01:58:59.114774",
    "archivo": "homicidios/homicidios_mucd_2025.pdf"
  },
  {
    "titulo": "Meta-síntesis de la labor de UNODC en México 2016-2023",
    "autor": "UNODC",
    "institucion": "UNODC",
    "anio": 2024,
    "url": "https://www.unodc.org/documents/evaluation/Meta-Analysis/UNODC_Work_in_Mexico_Meta_Synthesis.pdf",
    "categoria": "crimen_organizado",
    "numero_paginas": 88,
    "fecha_descarga": "2026-06-03T01:59:08.827589",
    "archivo": "crimen_organizado/crimen_organizado_unodc_2024.pdf"
  },
  {
    "titulo": "Violencia y participación electoral en Tierra Caliente",
    "autor": "Revista Mexicana de Ciencias Políticas y Sociales",
    "institucion": "UNAM",
    "anio": 2024,
    "url": "https://classic.scielo.org.mx/pdf/rmcps/v69n250/0185-1918-rmcps-69-250-281.pdf",
    "categoria": "tierra_caliente",
    "numero_paginas": 28,
    "fecha_descarga": "2026-06-03T01:59:11.628450",
    "archivo": "tierra_caliente/tierra_caliente_unam_2024.pdf"
  },
  {
    "titulo": "Electoral Violence and Illicit Influence in Mexico's Hot Land",
    "autor": "International Crisis Group",
    "institucion": "International Crisis Group",
    "anio": 2024,
    "url": "https://icg-prod.s3.amazonaws.com/089-mexico-hot-land.pdf",
    "categoria": "tierra_caliente",
    "numero_paginas": 33,
    "fecha_descarga": "2026-06-03T01:59:13.348506",
    "archivo": "tierra_caliente/tierra_caliente_international_crisis_group_2024.pdf"
  },
  {
    "titulo": "Manual sobre desplazamiento interno",
    "autor": "SCJN / ACNUR / CICR",
    "institucion": "SCJN",
    "anio": 2023,
    "url": "https://www.scjn.gob.mx/sites/default/files/publicaciones_scjn/publicacion/2023-03/Manual%20sobre%20desplazamiento%20interno.pdf",
    "categoria": "desplazamiento_forzado",
    "numero_paginas": 506,
    "fecha_descarga": "2026-06-03T01:59:17.191225",
    "archivo": "desplazamiento_forzado/desplazamiento_forzado_scjn_2023.pdf"
  },
  {
    "titulo": "Informe temático sobre desplazamiento forzado interno",
    "autor": "Colectivo EPUMX",
    "institucion": "Centro Prodh",
    "anio": 2023,
    "url": "https://centroprodh.org.mx/wp-content/uploads/2023/11/DesplazamientoForzado.pdf",
    "categoria": "desplazamiento_forzado",
    "numero_paginas": 38,
    "fecha_descarga": "2026-06-03T01:59:19.222662",
    "archivo": "desplazamiento_forzado/desplazamiento_forzado_centro_prodh_2023.pdf"
  },
  {
    "titulo": "La Extorsión Bajo el Caleidoscopio: muchas modalidades y pocas políticas públicas",
    "autor": "ONC",
    "institucion": "Observatorio Nacional Ciudadano",
    "anio": 2024,
    "url": "https://onc.org.mx/public/onc_site/uploads/extorsion_vf.pdf",
    "categoria": "extorsion",
    "numero_paginas": 150,
    "fecha_descarga": "2026-06-03T01:59:21.591513",
    "archivo": "extorsion/extorsion_observatorio_nacional_ciudadano_2024.pdf"
  },
  {
    "titulo": "Reporte de Delitos de Alto Impacto - 4T 2024",
    "autor": "ONC",
    "institucion": "Observatorio Nacional Ciudadano",
    "anio": 2025,
    "url": "https://onc.org.mx/public/onc_site/uploads/trimestrales/ReporteDAI4t_2024.pdf",
    "categoria": "extorsion",
    "numero_paginas": 82,
    "fecha_descarga": "2026-06-03T01:59:25.059124",
    "archivo": "extorsion/extorsion_observatorio_nacional_ciudadano_2025.pdf"
  },
  {
    "titulo": "Reporte Anual de Delitos 2024",
    "autor": "Integralia",
    "institucion": "Integralia",
    "anio": 2025,
    "url": "https://integralia.com.mx/web/wp-content/uploads/2025/02/17FEB25_Reporte-anual_Delitos-2024_VF.pdf",
    "categoria": "extorsion",
    "numero_paginas": 26,
    "fecha_descarga": "2026-06-03T01:59:27.627836",
    "archivo": "extorsion/extorsion_integralia_2025.pdf"
  },
  {
    "titulo": "El negocio de la militarización: Opacidad, poder y dinero",
    "autor": "MUCD",
    "institucion": "México Unido Contra la Delincuencia",
    "anio": 2024,
    "url": "https://www.mucd.org.mx/wp-content/uploads/2024/02/Negocio2.0.pdf",
    "categoria": "militarizacion",
    "numero_paginas": 139,
    "fecha_descarga": "2026-06-03T01:59:31.612846",
    "archivo": "militarizacion/militarizacion_m_xico_unido_contra_la_delincuencia_2024.pdf"
  },
  {
    "titulo": "Militarización y militarismo en México",
    "autor": "Lisa Sánchez y Gerardo Álvarez",
    "institucion": "Fundación Carolina",
    "anio": 2023,
    "url": "https://www.fundacioncarolina.es/wp-content/uploads/2023/06/Militarizacion.pdf",
    "categoria": "militarizacion",
    "numero_paginas": 192,
    "fecha_descarga": "2026-06-03T01:59:39.861448",
    "archivo": "militarizacion/militarizacion_fundaci_n_carolina_2023.pdf"
  },
  {
    "titulo": "Ley General para la Prevención Social de la Violencia y la Delincuencia",
    "autor": "Cámara de Diputados",
    "institucion": "Cámara de Diputados",
    "anio": 2021,
    "url": "https://www.diputados.gob.mx/LeyesBiblio/pdf/LGPSVD_040521.pdf",
    "categoria": "prevencion_social",
    "numero_paginas": 13,
    "fecha_descarga": "2026-06-03T01:59:41.103483",
    "archivo": "prevencion_social/prevencion_social_c_mara_de_diputados_2021.pdf"
  },
  {
    "titulo": "ENSU Primer Trimestre 2024",
    "autor": "INEGI",
    "institucion": "INEGI",
    "anio": 2024,
    "url": "https://www.inegi.org.mx/contenidos/saladeprensa/boletines/2024/ENSU/ENSU2024_04.pdf",
    "categoria": "violencia_urbana",
    "numero_paginas": 23,
    "fecha_descarga": "2026-06-03T01:59:43.284352",
    "archivo": "violencia_urbana/violencia_urbana_inegi_2024.pdf"
  },
  {
    "titulo": "Sembrando Vida en municipios con antecedentes de cultivos ilícitos",
    "autor": "Paul Frissard Martínez",
    "institucion": "Noria Research",
    "anio": 2023,
    "url": "https://noria-research.com/wp-content/uploads/2023/09/NORIA_MXCA_SEMBRANDO_VIDA_INFORME_SEPT_23_ES.pdf",
    "categoria": "violencia_rural",
    "numero_paginas": 49,
    "fecha_descarga": "2026-06-03T01:59:56.227054",
    "archivo": "violencia_rural/violencia_rural_noria_research_2023.pdf"
  },
  {
    "titulo": "Hallazgos 2023: Seguimiento del sistema de justicia penal",
    "autor": "México Evalúa",
    "institucion": "México Evalúa",
    "anio": 2024,
    "url": "https://www.mexicoevalua.org/wp-content/uploads/2024/10/HALLAZGOS2023.pdf",
    "categoria": "subregistro",
    "numero_paginas": 207,
    "fecha_descarga": "2026-06-03T02:00:00.704840",
    "archivo": "subregistro/subregistro_m_xico_eval_a_2024.pdf"
  },
  {
    "titulo": "Hallazgos 2022: Seguimiento del sistema de justicia penal",
    "autor": "México Evalúa",
    "institucion": "México Evalúa",
    "anio": 2023,
    "url": "https://www.mexicoevalua.org/wp-content/uploads/2023/10/HALLAZGOS2022.pdf",
    "categoria": "registro_victimas",
    "numero_paginas": 234,
    "fecha_descarga": "2026-06-03T02:00:04.137386",
    "archivo": "registro_victimas/registro_victimas_m_xico_eval_a_2023.pdf"
  },
  {
    "titulo": "(In) Seguridad pública en México, 2018-2024: Un balance de la gestión",
    "autor": "México Evalúa",
    "institucion": "México Evalúa",
    "anio": 2024,
    "url": "https://www.mexicoevalua.org/wp-content/uploads/2024/12/balance-seguridad-amlo.pdf",
    "categoria": "impacto_socioeconomico",
    "numero_paginas": 79,
    "fecha_descarga": "2026-06-03T02:00:05.845336",
    "archivo": "impacto_socioeconomico/impacto_socioeconomico_m_xico_eval_a_2024.pdf"
  },
  {
    "titulo": "Mexico Peace Index 2024",
    "autor": "Institute for Economics & Peace",
    "institucion": "IEP",
    "anio": 2024,
    "url": "https://reliefweb.int/attachments/58a529cb-f646-4c09-8333-90860794d902/MPI-ENG-2024-web-130524.pdf",
    "categoria": "impacto_socioeconomico",
    "numero_paginas": 100,
    "fecha_descarga": "2026-06-03T02:00:08.657194",
    "archivo": "impacto_socioeconomico/impacto_socioeconomico_iep_2024.pdf"
  },
  {
    "titulo": "Mexico Poverty and Equity Assessment",
    "autor": "World Bank",
    "institucion": "World Bank",
    "anio": 2024,
    "url": "https://documents1.worldbank.org/curated/en/099021925181518988/pdf/P179488-c49ff360-e38a-4961-85e2-1ef4e6cc5294.pdf",
    "categoria": "impacto_socioeconomico",
    "numero_paginas": 96,
    "fecha_descarga": "2026-06-03T02:00:10.797144",
    "archivo": "impacto_socioeconomico/impacto_socioeconomico_world_bank_2024.pdf"
  },
  {
    "titulo": "Humanitarian Report 2024 Mexico - ICRC",
    "autor": "ICRC",
    "institucion": "ICRC",
    "anio": 2024,
    "url": "https://www.icrc.org/sites/default/files/document_new/file_list/balancehumanitario.ingles_mexico.2024.pdf",
    "categoria": "impacto_socioeconomico",
    "numero_paginas": 15,
    "fecha_descarga": "2026-06-03T02:00:14.778088",
    "archivo": "impacto_socioeconomico/impacto_socioeconomico_icrc_2024.pdf"
  },
  {
    "titulo": "Mexico 2024 Human Rights Report",
    "autor": "U.S. Department of State",
    "institucion": "U.S. State Department",
    "anio": 2025,
    "url": "https://www.state.gov/wp-content/uploads/2025/08/624521_MEXICO-2024-HUMAN-RIGHTS-REPORT.pdf",
    "categoria": "impacto_socioeconomico",
    "numero_paginas": 20,
    "fecha_descarga": "2026-06-03T02:00:16.198813",
    "archivo": "impacto_socioeconomico/impacto_socioeconomico_u.s._state_department_2025.pdf"
  },
  {
    "titulo": "ENVIPE 2024: Encuesta Nacional de Victimización y Percepción sobre Seguridad Pública",
    "autor": "INEGI",
    "institucion": "INEGI",
    "anio": 2024,
    "url": "https://www.inegi.org.mx/contenidos/saladeprensa/boletines/2024/ENVIPE/ENVIPE_24.pdf",
    "categoria": "cifra_negra",
    "numero_paginas": 32,
    "fecha_descarga": "2026-06-03T02:00:33.131825",
    "archivo": "cifra_negra/cifra_negra_inegi_2024.pdf"
  }
]